{
  "base_commit": "ba0e11dc566c6808fa445404b45f114ed32b2dcd",
  "commit_shas": [
    "d6fa461f96b0bef2bae66a3410580798b97fac9b"
  ],
  "commits": [
    {
      "files": [
        "src/commands_state.rs"
      ],
      "sha": "d6fa461f96b0bef2bae66a3410580798b97fac9b",
      "short_sha": "d6fa461",
      "source_files": [
        "src/commands_state.rs"
      ],
      "subject": "Day 113 (23:00): Tighten `state why last-failure` messaging when incomplete runs exist (Task 1)"
    }
  ],
  "eval": {
    "reason": "The diff changes the first line from \"no state event found for 'last-failure'\" to \"No completed failure sessions found.\" only for last-failure queries, matching all success criteria. Two test assertions are updated and pass. No behavioral regression for completed-failure or other-ID paths.",
    "verdict": "PASS"
  },
  "gnome_deltas": {},
  "head_commit": "d6fa461f96b0bef2bae66a3410580798b97fac9b",
  "issue": "none",
  "phase": "task",
  "planned_files": [
    "src/commands_state.rs"
  ],
  "revert_reason": null,
  "source_files": [
    "src/commands_state.rs"
  ],
  "status": "completed",
  "task_file_title": "Tighten `state why last-failure` messaging when incomplete runs exist",
  "task_id": "task_01",
  "task_number": 1,
  "task_title": "Tighten `state why last-failure` messaging when incomplete runs exist",
  "touched_files": [
    "src/commands_state.rs"
  ]
}
