{
  "base_commit": "e9c3cb4bbef08db95a14ed8f523d171237fa5f1d",
  "commit_shas": [
    "749260aca059e010f4093ec0492fcf28360ec6e0"
  ],
  "commits": [
    {
      "files": [
        "src/commands_state.rs",
        "src/state.rs"
      ],
      "sha": "749260aca059e010f4093ec0492fcf28360ec6e0",
      "short_sha": "749260a",
      "source_files": [
        "src/commands_state.rs",
        "src/state.rs"
      ],
      "subject": "Day 109 (16:49): Improve cold-start state failure diagnostics (Task 1)"
    }
  ],
  "eval": {
    "reason": "Implementation adds StateDirectoryInfo diagnostics in state.rs and replaces the generic cold-start message in handle_why with a three-branch check (no dir / dir exists no events / events unreadable), giving actionable next steps. All tests pass (commands_state: 168 passed, state: 287 passed), cargo check clean, changes scoped to the two listed files.",
    "verdict": "PASS"
  },
  "gnome_deltas": {},
  "head_commit": "749260aca059e010f4093ec0492fcf28360ec6e0",
  "issue": "none",
  "phase": "task",
  "planned_files": [
    "src/commands_state.rs",
    "src/state.rs"
  ],
  "revert_reason": null,
  "source_files": [
    "src/commands_state.rs",
    "src/state.rs"
  ],
  "status": "completed",
  "task_file_title": "Improve cold-start state failure diagnostics",
  "task_id": "task_01",
  "task_number": 1,
  "task_title": "Improve cold-start state failure diagnostics",
  "touched_files": [
    "src/commands_state.rs",
    "src/state.rs"
  ]
}
