{
  "artifact_path": "tasks/task_01/task.md",
  "body_preview": "Add a `yyds state failures tools [--limit N]` subcommand that filters ToolCallCompleted state events with error/failure payloads, showing tool name, error type, run context, and timestamps. This makes state-recorded tool failures visible at the CLI, enabling agents to reconcile the 16 state-only vs 1 transcript-only tool-failure gap identified by graph press",
  "expected_evidence": "Future `state failures tools` output shows tool-level failure detail that agents can act on Graph-derived tool-failure pressure charts converge (state-only count becomes reconcilable) Dashboard tool-failure reconciliation metrics move toward 0 discrepancy Implementation Notes: Extend the `handle_failures` function in `src/commands_state.rs` to accept `tools`",
  "files": [
    "src/commands_state.rs",
    "src/state.rs"
  ],
  "issue": "none",
  "origin": "planner",
  "quality": {
    "assessment_alignment": {
      "contradicted_by_assessment": false,
      "evidence": []
    },
    "generic_self_improvement": false,
    "has_expected_evidence": true,
    "has_goal": true,
    "has_success_criteria": true,
    "has_verification": true,
    "score": 1.0
  },
  "session_plan_path": "session_plan/task_01.md",
  "task_id": "task_01",
  "task_number": 1,
  "title": "Add state failures tools subcommand for tool-failure reconciliation"
}
