{
  "artifact_path": "tasks/task_01/task.md",
  "body_preview": "- Trajectory state_run_incomplete_count=1 with open_after_SessionStarted=1 - Graph-derived next-task pressure #1: \"Close yyds state and model lifecycle gaps\" - Assessment confirms: \"close_orphaned_run_if_needed only scans for RunStarted events, but SessionStarted is emitted later. A session that crashes after SessionStarted but before RunCompleted leaves an ",
  "declared_files": [
    "src/state.rs"
  ],
  "expected_evidence": "Future structured state snapshots show state_run_incomplete_count moving to 0 \"Close yyds state and model lifecycle gaps\" drops off graph-derived pressure No new open_after_SessionStarted instances appear Implementation Notes: The fix is surgical \u2014 roughly 5-8 lines changed in the backward scan loop. When scanning backward through events looking for lifecycl",
  "files": [
    "src/state.rs"
  ],
  "issue": "#83",
  "origin": "planner (refined from harness-seed)",
  "quality": {
    "analysis_only_escape": false,
    "assessment_alignment": {
      "contradicted_by_assessment": false,
      "evidence": []
    },
    "generic_self_improvement": false,
    "has_expected_evidence": true,
    "has_goal": true,
    "has_success_criteria": true,
    "has_verification": true,
    "score": 1.0
  },
  "session_plan_path": "session_plan/task_01.md",
  "task_id": "task_01",
  "task_number": 1,
  "title": "Recognize SessionStarted as lifecycle start in orphan-run detection"
}
